atomgrad/__init__.py
atomgrad/atom.py
atomgrad/graph.py
atomgrad/metrics.py
atomgrad/nn.py
atomgrad/optim.py
atomgrad-0.3.0.dist-info/METADATA
atomgrad-0.3.0.dist-info/WHEEL
atomgrad-0.3.0.dist-info/top_level.txt
atomgrad-0.3.0.dist-info/RECORD
