Metadata-Version: 2.1
Name: atomgrad
Version: 0.3.0
Summary: An autocgrad engine that is between micrograd and tinygrad with a PyTorch-like neural network API:)
Home-page: https://github.com/tanaydesai/atomgrad
Author: Tanay Desai
Classifier: Programming Language :: Python :: 3
Classifier: License :: OSI Approved :: MIT License
Classifier: Operating System :: OS Independent
Requires-Python: >=3.6
